tunic_language/IPA.runes
tunic_language/__init__.py
tunic_language/cmudict.IPA
tunic_language/cmudict.phones
tunic_language/mappings.py
tunic_language/translation.py
tunic_language_YI_JIAHE-0.0.5.dist-info/METADATA
tunic_language_YI_JIAHE-0.0.5.dist-info/WHEEL
tunic_language_YI_JIAHE-0.0.5.dist-info/top_level.txt
tunic_language_YI_JIAHE-0.0.5.dist-info/RECORD
