Metadata-Version: 2.1
Name: tunic-language-YI-JIAHE
Version: 0.0.5
Summary: Tools for working with the tunic language
Home-page: https://github.com/pypa/sampleproject
Author: Yi Jiahe
Project-URL: Bug Tracker, https://github.com/pypa/sampleproject/issues
Classifier: Programming Language :: Python :: 3
Classifier: License :: OSI Approved :: MIT License
Classifier: Operating System :: OS Independent
Requires-Python: >=3.7
Requires-Dist: nltk
